padpoes/__init__.py
padpoes/__main__.py
padpoes/checkers/__init__.py
padpoes/checkers/baseclass.py
padpoes/checkers/empty.py
padpoes/checkers/fuzzy.py
padpoes/checkers/glossary.py
padpoes/checkers/linelength.py
padpoes/checkers/nbsp.py
padpoes/github.py
padpoes/padpo.py
padpoes/pofile.py
padpoes-0.12.0.dist-info/entry_points.txt
padpoes-0.12.0.dist-info/LICENSE
padpoes-0.12.0.dist-info/WHEEL
padpoes-0.12.0.dist-info/METADATA
padpoes-0.12.0.dist-info/RECORD
