Metadata-Version: 2.1
Name: padpoes
Version: 0.12.0
Summary: Linter for gettext files
Home-page: https://github.com/bgeninatti/padpo
License: BSD-3-Clause
Keywords: gettext,linter
Author: Vincent Poulailleau
Author-email: vpoulailleau@gmail.com
Requires-Python: >=3.7,<4.0
Classifier: License :: OSI Approved :: BSD License
Classifier: Operating System :: OS Independent
Classifier: Programming Language :: Python :: 3
Classifier: Programming Language :: Python :: 3.7
Classifier: Programming Language :: Python :: 3.8
Classifier: Programming Language :: Python :: 3.9
Requires-Dist: requests (>=2.20.0,<3.0.0)
Requires-Dist: simplelogging (>=0.10,<0.12)
Project-URL: Documentation, https://github.com/bgeninatti/padpo
Project-URL: Repository, https://github.com/bgeninatti/padpo
